signal_backtester/__init__.py
signal_backtester/base/__init__.py
signal_backtester/base/base_backtester.py
signal_backtester/base/base_strategy.py
signal_backtester/core/__init__.py
signal_backtester/core/operations.py
signal_backtester/core/picker.py
signal_backtester/core/runner.py
signal_backtester/schemas/__init__.py
signal_backtester/schemas/models.py
signal_backtester/strategies/__init__.py
signal_backtester/strategies/one_sided.py
signal_backtester/strategies/two_sided.py
signal_backtester-1.0.4.dist-info/LICENSE
signal_backtester-1.0.4.dist-info/METADATA
signal_backtester-1.0.4.dist-info/WHEEL
signal_backtester-1.0.4.dist-info/top_level.txt
signal_backtester-1.0.4.dist-info/RECORD
