Metadata-Version: 2.1
Name: signal-backtester
Version: 1.0.4
Summary: tiny library for fast backtest on generated signals
Home-page: https://github.com/xibalbas/signal_backtester
Author: Ali moradi
Author-email: ali.mrd318@gmail.com
License: UNKNOWN
Project-URL: Bug Tracker, https://github.com/xibalbas/signal_backtester/issues
Platform: UNKNOWN
Classifier: Programming Language :: Python :: 3
Classifier: License :: OSI Approved :: MIT License
Classifier: Operating System :: OS Independent
Requires-Python: >=3.7
License-File: LICENSE
Requires-Dist: backtesting
Requires-Dist: pydantic
